Workbook

Sheet 问题记录
A1: 序号 | B1: 问题 | C1: 问题描述 | D1: 问题类型 | E1: 建议策略 | F1: 状态 | G1: 备注
A2: 1 | B2: Object type覆盖不全 | C2: Object type对应到EAM的业务对象，存在基础数据、报告数据不能识别为业务对象，无法映射到Object type； | D2: 本体元素映射问题 | E2: ---基础数据对标采用palantir的shareproperty来管理，但如何实现，还需要验证； --报告数据：暂定为Object type | F2: 验证中
A3: 2 | B3: 非主逻辑实体的映射 | C3: Ontology的元模型中，没有EAM逻辑实体对应的本体元素，如果采用Object typ-Property的两层结构，业务对象中的非主逻辑实体（比如合同的付款条款），需要先将其映射为一个ObjectType类型的属性，然后再展开分解里面的属性。 | D3: 本体元素映射问题 | E3: 非主逻辑实体（比如合同的付款条款），需要先将其映射为一个ObjectType类型的属性，然后再展开分解里面的属性。 | F3: 验证中
A4: 3 | B4: 识别业务流程不准确 | C4: 如果不是业务专家，从数据库识别业务流程，输入源有限，识别结果不准确、不完整。 | D4: 建模质量问题 | E4: 1、承接企业架构的规划设计成果； 2、除了数据库相关内容外，需要补充输入源 3、有业务专家参与
A5: 4 | B5: 识别业务规则不完整、准确 | C5: 如果不是业务专家，从数据库识别业务规则，输入源有限，识别结果不准确、不完整。 | D5: 建模质量问题 | E5: 1、对规则进行分类，比如对数据的约束，如编码规则、唯一性、空缺值等约束规则，可以从数据库识别，固化即可；
A6: 5 | B6: 指标识别不全 | C6: 建模人员可以基于数据库，识别一些简单的原子指标，但对指标的统计口径（统计范围），很难做精准的业务定义，依赖于业务架构的定义。 | D6: 建模质量问题 | E6: 1、承接企业架构的指标设计成果； 2、基于业务统计分析的需求，梳理提炼指标，补充完善指标定义； 3、有业务专家参与定义指标
A7: 6 | B7: 行动类型识别不完整 | C7: 可以基于数据库表结构、已经数据库的样本数据、状态值等输入，识别一些行动类型（对数据的操作），但识别结果不完整、对行动类型的业务涵义定义也不精准。 | D7: 建模质量问题

Sheet 建模总结
A1: 本体元素 | B1: 人工建模过程 | C1: 建模难点 | D1: 能否基于IT系统产出 | E1: 输入内容 | F1: 输入物价值 | G1: 备注
A2: 对象类型 | B2: 基于输入的数据库表结构或者数据模型、字典，按照业务对象的识别原则，进行识别，并且进行定义 | C2: 1、如果给出的数据库表缺少表名、字段名注释，很多理解其含义和用途，识别不准确； 2、如果数据库表做了冗余、多表合并，需要做拆分提炼对象类型（如果拆分出库单、入库单、调拨单）； 3、建模人员需要掌握一定的业务领域知识 | D2: 可以 | E2: 数据模型 | F2: 高 | G2: EAM的数据模型，价值最高，可以直接转换为本体模型
E3: 数据字典 | F3: 高 | G3: 源系统提供的数据字典，可读性好，但还需要提炼、建模
E4: 数据库表结构 | F4: 中 | G4: 数据库表结构，通常还需要补充注释、业务解读，才能提炼、建模
A5: 链接类型 | B5: 基于识别的对象类型、输入的数据库表关系（或者逻辑实体关系），识别链接类型 | C5: 1、数据库表里面没有建立主外键关系； 2、数据模型中的ER关系，不能显式的表达业务行为关系（比如合同“约定”付款条款） 3、识别的链接类型不完整； 4、建模人员需要掌握一定的业务领域知识 | D5: 可以 | E5: 数据模型 | F5: 高 | G5: EAM的数据模型，价值最高，可以直接转换为本体模型
E6: 数据字典 | F6: 高 | G6: 源系统提供的数据字典，可读性好，但还需要提炼、建模
E7: 数据库表结构 | F7: 中 | G7: 数据库表结构，通常还需要补充注释、业务解读，才能提炼、建模
A8: 属性 | B8: 基于识别的对象类型、链接类型，以及数据字典/数据库表/数据模型结构，细化、识别、定义属性 | C8: 1、如果给出的数据库表缺少表名、字段名注释，很多理解其含义和用途，识别不准确； 2、同一个属性（比如客户编码），在多个数据表中，名称、类型、长度、解释都不统一，导致属性定义时不知以谁为准。 | D8: 可以 | E8: 数据模型 | F8: 高 | G8: EAM的数据模型，价值最高，可以直接转换为本体模型
E9: 数据字典 | F9: 高 | G9: 源系统提供的数据字典，可读性好，但还需要提炼、建模
E10: 数据库表结构 | F10: 中 | G10: 数据库表结构，通常还需要补充注释、业务解读，才能提炼、建模
A11: 术语 | B11: 1、基于业务领域和范围，识别重要术语，进行定义； 2、基于后续的Ontology模型中涉及到的术语，补充进行定义； | C11: 1、对术语的定义，需要有丰富业务领域经验，否则定义的术语不精准； 2、业务领域内的术语条目很多，需要进行粪门别类的管理，需要设计分类标准； | D11: 可以 | E11: 数据模型 | F11: 高 | G11: EAM的数据模型，价值最高，可以直接转换为本体模型
E12: 数据字典 | F12: 中 | G12: 源系统提供的数据字典，涉及到的业务术语名称可能不规范、术语解释不完整，需要从业务视角进行标准化、完善
E13: 数据库表结构 | F13: 中 | G13: 数据库表结构，通常还需要术语名称标准化、补充注释、业务解读，才能提炼、建模
A14: 业务规则
A15: 业务流程
A16: 行动类型
A17: 指标
A18: 维度

Sheet 术语
A1: 能通过业务对象、属性、指标的定义，识别业务术语
A2: 术语编码 | B2: 术语名称 | C2: 别名 | D2: 英文名 | E2: 术语定义 | F2: 术语分类 | G2: 解释部门 | H2: 来源、输入 | I2: 打分
B3: 客户 | E3: 购买企业产品、服务或与企业发生交易往来，接受企业交付成果的个人、企业或其他法人实体，是企业销售业务的核心对象。
B4: 供应商 | E4: 为企业提供物料、商品、服务或资源，与企业存在采购合作关系的外部法人、组织或个人，是企业供应链上游的核心主体。
B5: 物料 | E5: 企业在生产、经营、库存管理中涉及的原材料、半成品、成品、备品备件、辅助材料等可计量、可管理的物品统称。
B6: 产品线 | E6: 由一组功能相近、面向同类市场、满足同类需求、可归为一类管理的产品所构成的产品集合，用于产品分类与业务规划。
B7: 组织 | E7: 企业内部承担特定职能、具备管理边界的机构单元，包含公司、部门、事业部、分厂、门店等，是权责与业务执行的载体。
B8: 采购订单 | E8: 企业向供应商发起采购需求时生成的正式单据，明确物料、数量、价格、交货期、交付方式等采购约定，是采购执行的依据。
B9: 销售订单 | E9: 企业与客户达成销售意向后生成的业务单据，记录产品、数量、价格、交货信息、结算方式等交易约定，是销售履约的依据。
B10: 仓库 | E10: 企业用于存放、保管、收发物料与成品的物理或逻辑存储空间，具备库位、库存、出入库管理能力，是仓储管理核心对象。
B11: 入库单 | E11: 记录物料、成品等物资进入仓库的明细单据，包含来源、品类、数量、仓库、经办人等信息，是库存增加的凭证。
B12: 出库单 | E12: 记录物料、成品等物资从仓库发出的明细单据，包含去向、品类、数量、仓库、用途等信息，是库存减少的凭证。

Sheet 业务规则
A1: 建模问题：在IT系统的数据库，数据规则很隐式，虽然可以通过建模人员的业务领域经验做识别，很难识别准确、完整。
A2: 规则编号 | B2: 规则名称 | C2: 规则描述 | D2: 所属活动编号 | E2: 活动名称 | F2: 规则分类 | G2: 解释部门
A3: R001 | B3: 采购需求合规性审核规则 | C3: 需求部门提报采购需求后，需经财务部（预算匹配性）、业务主管部门（需求必要性）双维度审核通过，方可进入采购寻源环节 | E3: 需求审核 | F3: 流程控制 | G3: 采购部
A4: R002 | B4: 供应商资质准入规则 | C4: 新供应商准入需提供营业执照、行业资质证书、税务登记证明等材料，通过资质完整性+合规性评分（满分100分，≥80分准入） | E4: 资质审核 | F4: 准入控制 | G4: 采购部
A5: R003 | B5: 采购合同金额分级审核规则 | C5: 采购合同金额＜50万元时，由采购部负责人+法务专员双签；≥50万元时，需追加总经理终审，重点审核付款条款、违约责任等核心内容 | E5: 合同签署 | F5: 风险控制 | G5: 法务部
A6: R004 | B6: 到货验收异常处置规则 | C6: 货物到货后，若出现数量短缺（偏差＞5%）、规格不符（与订单技术参数不一致）、质检不合格（无合格报告/报告结论不合格），仓库有权拒收并触发退换货流程 | E6: 到货检验 | F6: 质量管控 | G6: 质检部
A7: R005 | B7: 入库单据匹配规则 | C7: 物资办理入库时，需同步核对采购订单（订单号、物料编码）、供应商送货单（送货数量、批次）、质检报告（合格标识），三单信息完全一致方可完成系统入库 | E7: 单据核对 | F7: 流程控制 | G7: 仓库部
A8: R006 | B8: 危险化学品存储规则 | C8: 易燃易爆、有毒有害类危险化学品，必须存储于防爆/防腐专用仓库，与普通物资库间距≥10米，且执行“双人双锁+每日巡检”管理机制 | E8: 库区规划 | F8: 安全管控 | G8: 仓储部
A9: R007 | B9: 贵重物资出库审批规则 | C9: 单价≥1万元的贵重物资（如精密仪器、高端原材料），领用时除常规《领料单》外，需附加部门总监审批单+《使用用途说明》，仓库核验后方可出库 | E9: 出库审批 | F9: 权限控制 | G9: 仓库部
A10: R008 | B10: 月度盘点差异追溯规则 | C10: 每月末盘点中，若某类物资账面数与实盘数差异率绝对值＞1%（差异率=账面数 - 实盘数÷账面数×100%），需在3个工作日内提交《差异分析报告》，明确责任环节及整改措施 | E10: 盘点分析

Sheet 业务对象（对象类型）
A1: 建模问题：基础数据、报告数据不能识别为业务对象，无法映射到Object type
A2: 业务对象编号 | B2: 业务对象名称 | C2: 业务对象编号 | D2: 业务对象英文名 | E2: 业务对象定义 | F2: 业务对象类型 | G2: 关联物理表
A3: BO0001 | B3: 客户 | C3: =A3 -> BO0001 | E3: 购买企业产品、服务或与企业发生交易往来，接受企业交付成果的个人、企业或其他法人实体，是企业销售业务的核心对象。 | G3: T_BD_Customer,T_BD_CustomerOrg
A4: BO0002 | B4: 供应商 | C4: =A4 -> BO0002 | E4: 为企业提供物料、商品、服务或资源，与企业存在采购合作关系的外部法人、组织或个人，是企业供应链上游的核心主体。 | G4: T_BD_Supplier
A5: BO0003 | B5: 物料 | C5: =A5 -> BO0003 | E5: 企业在生产、经营、库存管理中涉及的原材料、半成品、成品、备品备件、辅助材料等可计量、可管理的物品统称。 | G5: T_BD_Material,T_BD_MaterialOrg
A6: BO0004 | B6: 产品线 | C6: =A6 -> BO0004 | E6: 由一组功能相近、面向同类市场、满足同类需求、可归为一类管理的产品所构成的产品集合，用于产品分类与业务规划。 | G6: T_BD_ProductLine
A7: BO0005 | B7: 组织 | C7: =A7 -> BO0005 | E7: 企业内部承担特定职能、具备管理边界的机构单元，包含公司、部门、事业部、分厂、门店等，是权责与业务执行的载体。 | G7: T_ORG_Organizations
A8: BO0006 | B8: 采购订单 | C8: =A8 -> BO0006 | E8: 企业向供应商发起采购需求时生成的正式单据，明确物料、数量、价格、交货期、交付方式等采购约定，是采购执行的依据。 | G8: T_PUR_POOrder，T_PUR_POOrderEntry
A9: BO0007 | B9: 销售订单 | C9: =A9 -> BO0007 | E9: 企业与客户达成销售意向后生成的业务单据，记录产品、数量、价格、交货信息、结算方式等交易约定，是销售履约的依据。 | G9: T_SAL_Order，T_PUR_POOrderEntry
A10: BO0008 | B10: 仓库 | C10: =A10 -> BO0008 | E10: 企业用于存放、保管、收发物料与成品的物理或逻辑存储空间，具备库位、库存、出入库管理能力，是仓储管理核心对象。 | G10: T_STK_Inventory
A11: BO0009 | B11: 入库单 | C11: =A11 -> BO0009 | E11: 记录物料、成品等物资进入仓库的明细单据，包含来源、品类、数量、仓库、经办人等信息，是库存增加的凭证。 | G11: T_STK_InvMovement
A12: BO0010 | B12: 出库单 | C12: =A12 -> BO0010 | E12: 记录物料、成品等物资从仓库发出的明细单据，包含去向、品类、数量、仓库、用途等信息，是库存减少的凭证。 | G12: T_STK_InvMovement
A13: BO0011 | B13: 库存快照 | C13: =A13 -> BO0011 | E13: 按期间和物料的库存结存情况,含数量、金额、批次、最早入库日期 | F13: 数据模型 | G13: T_STK_Inventory
A14: BO0012 | B14: 库存风险物料预警 | C14: =A14 -> BO0012 | E14: 呆滞库存、不良品库存和待退仓的预警数据 | F14: 数据模型 | G14: T_STK_SlowMoving
A15: BO0013 | B15: 安全库存预警 | C15: =A15 -> BO0013 | E15: 按物料输出即将低于安全库存及已经低于安全库存的物料清单 | G15: T_STK_InvMovement
A16: BO0014 | B16: 应收单 | C16: =A16 -> BO0014 | E16: 因销售而应向客户收取的款项,含开票金额、已收款、票据金额、逾期天数 | G16: T_AR_Receivable
A17: BO0015 | B17: 应付单 | C17: =A17 -> BO0015 | E17: 应付单据,含供应商、金额、公共标识 | F17: 数据模型 | G17: T_AP_Payable
A18: BO0016 | B18: 会计科目 | C18: =A18 -> BO0016 | E18: 科目主数据,同时具有财务分类和管报分类 | F18: 数据模型 | G18: T_BD_Account
A19: BO0017 | B19: 会计期间 | C19: =A19 -> BO0017 | E19: 期间主数据,含年月和关账标识 | F19: 数据模型 | G19: T_BD_Period
A20: BO0018 | B20: 分摊规则 | C20: =A20 -> BO0018 | E20: 费用和收入分摊的规则引擎,含门槛值和回退机制 | F20: 数据模型 | G20: T_FM_AllocRule
A21: BO0019 | B21: 预算 | C21: =A21 -> BO0019 | E21: 按期间/组织/科目编制的预算金额,支持多版本 | F21: 数据模型 | G21: T_FM_Budget
A22: BO0020 | B22: 滚动预测 | C22: =A22 -> BO0020 | E22: N+3滚动预测数据,按轮次存储,来源CRM/模板/人工 | F22: 数据模型 | G22: T_FM_Forecast
A23: BO0021 | B23: 现金流量表 | C23: =A23 -> BO0021 | E23: 按事业部的经营现金流数据,含收款、付款、费用、折摊 | F23: 数据模型 | G23: T_FM_CashFlow
A24: BO0022 | B24: 总账余额 | C24: =A24 -> BO0022 | E24: 对接金蝶总账的科目余额数据,按期间/科目/组织存储借贷金额 | F24: 数据模型 | G24: T_GL_Balance

Sheet 业务属性（属性）
A1: 建模问题：业务对象中的非主逻辑实体，需要先将其映射为一个ObjectType类型的属性，然后再展开分解里面的属性。
A2: 业务对象编号 | B2: 逻辑实体编号 | C2: 逻辑实体名称 | D2: 逻辑实体英文名 | E2: 业务属性编号 | F2: 业务属性名称 | G2: 属性英文名 | H2: 业务属性定义 | I2: 数据类型 | J2: 是否主键 | K2: 来源表名 | L2: 来源字段
A3: BO005 | B3: LE00001 | C3: 组织 | D3: organization | E3: AT00001 | F3: 组织内码 | G3: OrgId | H3: 组织唯一标识(GUID) | I3: NVARCHAR(36) | J3: Yes | K3: organization | L3: FOrgId
A4: BO005 | B4: LE00001 | C4: 组织 | D4: organization | E4: AT00002 | F4: 组织编码 | G4: OrgNumber | H4: 业务可读的组织编码 | I4: NVARCHAR(36) | J4: No | K4: organization | L4: FOrgNumber
A5: BO005 | B5: LE00001 | C5: 组织 | D5: organization | E5: AT00003 | F5: 组织名称 | G5: OrgName | H5: 组织名称 | I5: NVARCHAR(100) | J5: No | K5: organization | L5: FOrgName
A6: BO005 | B6: LE00001 | C6: 组织 | D6: organization | E6: AT00004 | F6: 组织类型 | G6: OrgType | H6: 类型(BU/分公司/合并主体) | I6: NVARCHAR(20) | J6: No | K6: organization | L6: FOrgType
A7: BO005 | B7: LE00001 | C7: 组织 | D7: organization | E7: AT00005 | F7: 上级组织 | G7: ParentOrgId | H7: 上级组织ID,支持多级 | I7: NVARCHAR(36) | J7: No | K7: organization | L7: FParentOrgId
A8: BO005 | B8: LE00001 | C8: 组织 | D8: organization | E8: AT00006 | F8: 是否启用 | G8: IsActive | H8: 是否启用 Y/N | I8: CHAR(1) | J8: No | K8: organization | L8: FIsActive
A9: BO004 | B9: LE00002 | C9: 产品线 | D9: product_line | E9: AT00007 | F9: 产品线内码 | G9: ProductLineId | H9: 产品线唯一标识 | I9: NVARCHAR(36) | J9: Yes | K9: product_line | L9: FProductLineId
A10: BO004 | B10: LE00002 | C10: 产品线 | D10: product_line | E10: AT00008 | F10: 产品线编码 | G10: ProductLineNO | H10: 产品线编码 | I10: NVARCHAR(30) | J10: No | K10: product_line | L10: FNumber
A11: BO004 | B11: LE00002 | C11: 产品线 | D11: product_line | E11: AT00009 | F11: 产品线名称 | G11: ProductLineName | H11: 产品线名称 | I11: NVARCHAR(100) | J11: No | K11: product_line | L11: FName
A12: BO004 | B12: LE00002 | C12: 产品线 | D12: product_line | E12: AT00010 | F12: 所属事业部 | G12: OrgId | H12: 所属事业部组织ID | I12: NVARCHAR(36) | J12: No | K12: product_line | L12: FOrgId
A13: BO003 | B13: LE00003 | C13: 物料 | D13: material | E13: AT00011 | F13: 物料内码 | G13: MaterialId | H13: 物料唯一标识 | I13: NVARCHAR(36) | J13: Yes | K13: material | L13: FMaterialId
... A70: BO010 | B70: LE00018 | C70: 出库单 | D70: Outbound_Order | E70: AT00067 | F70: 移动类型 | G70: MoveType | H70: 类型(采购入/销售出/调拨/报废) | I70: NVARCHAR(20) | J70: No | K70: Outbound_Order | L70: FMoveType

Sheet 实体关系(链接类型)
A1: 建模问题：只建立Object type之间的关系，而Object type内部各个实体关系，如头行结构，无法建立，是否影响AI使用？
A2: 关系编号 | B2: 源业务对象编号 | C2: 源业务对象名称 | E2: 目标业务对象编号 | F2: 目标业务对象名称 | H2: 关系类型 | I2: 关系描述 | J2: 关联属性
A3: ER001 | B3: LE00001 | C3: 组织 | D3: =VLOOKUP(C3,'业务对象（对象类型）'!B:C,2,FALSE) -> BO0005 | E3: LE00001 | F3: 组织 | G3: =VLOOKUP(F3,'业务对象（对象类型）'!B:C,2,FALSE) -> BO0005 | H3: 1:N | I3: 组织自引用(上下级) | J3: FParentOrgId -> FOrgId
A4: ER002 | B4: LE00001 | C4: 组织 | D4: =VLOOKUP(C4,'业务对象（对象类型）'!B:C,2,FALSE) -> BO0005 | E4: LE00002 | F4: 产品线 | G4: =VLOOKUP(F4,'业务对象（对象类型）'!B:C,2,FALSE) -> BO0004 | H4: 1:N | I4: 事业部拥有多条产品线 | J4: FOrgId->FOrgId
A5: ER007 | B5: LE00004 | C5: 客户 | D5: =VLOOKUP(C5,'业务对象（对象类型）'!B:C,2,FALSE) -> BO0001 | E5: LE00010 | F5: 销售订单 | G5: =VLOOKUP(F5,'业务对象（对象类型）'!B:C,2,FALSE) -> BO0007 | H5: 1:N | I5: 客户拥有多个销售订单 | J5: FCustomerId->FCustomerId
A6: ER008 | B6: LE00001 | C6: 组织 | D6: =VLOOKUP(C6,'业务对象（对象类型）'!B:C,2,FALSE) -> BO0005 | E6: LE00010 | F6: 销售订单 | G6: =VLOOKUP(F6,'业务对象（对象类型）'!B:C,2,FALSE) -> BO0007 | H6: 1:N | I6: 事业部拥有多个销售订单 | J6: FOrgId-FOrgId
A7: ER010 | B7: LE00003 | C7: 产品线 | D7: =VLOOKUP(C7,'业务对象（对象类型）'!B:C,2,FALSE) -> BO0004 | E7: LE00011 | F7: 销售订单 | G7: =VLOOKUP(F7,'业务对象（对象类型）'!B:C,2,FALSE) -> BO0007 | H7: 1:N | I7: 物料出现在销售分录中 | J7: FMaterialId->FMaterialId
A8: ER012 | B8: LE00005 | C8: 供应商 | D8: =VLOOKUP(C8,'业务对象（对象类型）'!B:C,2,FALSE) -> BO0002 | E8: LE00012 | F8: 采购订单 | G8: =VLOOKUP(F8,'业务对象（对象类型）'!B:C,2,FALSE) -> BO0006 | H8: 1:N | I8: 供应商拥有多个采购订单 | J8: FSupplierId->FSupplierId
A9: ER014 | B9: LE00003 | C9: 物料 | D9: =VLOOKUP(C9,'业务对象（对象类型）'!B:C,2,FALSE) -> BO0003 | E9: LE00013 | F9: 采购订单 | G9: =VLOOKUP(F9,'业务对象（对象类型）'!B:C,2,FALSE) -> BO0006 | H9: 1:N | I9: 物料出现在采购分录中 | J9: FMaterialId->FMaterialId
A10: ER021 | B10: LE00003 | C10: 物料 | D10: =VLOOKUP(C10,'业务对象（对象类型）'!B:C,2,FALSE) -> BO0003 | E10: LE00016 | F10: 仓库 | G10: =VLOOKUP(F10,'业务对象（对象类型）'!B:C,2,FALSE) -> BO0008 | H10: 1:N | I10: 物料有库存记录 | J10: FMaterialId->FMaterialId
A11: ER023 | B11: LE00003 | C11: 物料 | D11: =VLOOKUP(C11,'业务对象（对象类型）'!B:C,2,FALSE) -> BO0003 | E11: LE00017 | F11: 入库单 | G11: =VLOOKUP(F11,'业务对象（对象类型）'!B:C,2,FALSE) -> BO0009 | H11: 1:N | I11: 物料有出入库记录 | J11: FMaterialId->FMaterialId
A12: ER023 | B12: LE00003 | C12: 物料 | D12: =VLOOKUP(C12,'业务对象（对象类型）'!B:C,2,FALSE) -> BO0003 | E12: LE00017 | F12: 出库单 | G12: =VLOOKUP(F12,'业务对象（对象类型）'!B:C,2,FALSE) -> BO0010 | H12: 1:N | I12: 物料有出入库记录 | J12: FMaterialId->FMaterialId

Sheet 活动
A2: 活动编码 | B2: 活动名称 | C2: 活动描述 | D2: 上游活动编码 | E2: 业务角色 | F2: 操作业务对象编号 | G2: 操作业务对象名称
A3: A001 | B3: 采购订单创建 | C3: 采购专员根据审核通过的采购申请单创建采购订单 | E3: 采购专员 | G3: 采购订单
A4: A002 | B4: 采购订单审核 | C4: 采购主管审核采购订单的价格、条款等关键信息 | D4: A001 | E4: 采购主管 | G4: 采购订单
A5: A003 | B5: 采购订单下达供应商 | C5: 向供应商正式下达采购订单 | D5: A002 | E5: 采购专员 | G5: 采购订单
A6: A004 | B6: 采购订单变更 | C6: 处理采购订单的变更需求 | D6: A003 | E6: 采购专员 | G6: 采购订单
A7: A005 | B7: 采购订单关闭 | C7: 采购订单执行完成后进行关闭操作 | D7: A003 | E7: 采购专员 | G7: 采购订单

Sheet 行动类型
A1: 行动类型编码 | B1: 行动类型中文名称 | C1: 行动类型英文名称 | D1: 行动类型描述 | E1: 对象类型 | F1: 参数
B2: 创建采购订单
B3: 更新采购订单
B4: 删除采购订单
B5: 采购订单收货
B6: 采购订单入库
B7: 采购订单退货
B8: 采购订单部分退货

Sheet 指标
A1: 建模问题：建模人员可以基于数据库，识别一些简单的原子指标，但对指标的统计口径（统计范围），很难做精准的业务定义，依赖于业务架构的定义。
A2: 指标编码 | B2: 指标名称 | C2: 指标别名 | D2: 指标英文名 | E2: 指标定义 | F2: 计算公式(业务) | G2: 统计口径 | H2: 指标类型(1为复合指标,2为原子指标) | I2: 计算公式(技术) | J2: 对应表名 | K2: 聚合列 | L2: 聚合类型 | M2: 连接条件 | N2: 筛选条件 | O2: 维度列 | P2: 版本 | Q2: 修改说明
A3: M001 | B3: 采购金额 | C3: 采购总金额、应付采购款 | D3: Purchase Amount | E3: 企业在一定周期内，向供应商采购物料、商品及相关服务所发生的实际应付或已付总金额，是反映企业采购成本的核心指标。 | F3: 采购金额 = 当期所有采购订单金额（含税）累计 | G3: 1. 周期：可按日、周、月、季度、年度统计； 2. 范围：企业所有组织单元发起的采购订单，不含作废、取消的采购订单； 3. 计价：默认按不含税金额统计； | H3: 2 | J3: T_PUR_POOrderEntry | K3: FAmount | L3: SUM
A4: M002 | B4: 销售收入 | C4: 销售总营收、销售回款（不含未回款部分） | D4: Sales Revenue | E4: 企业向客户销售产品、提供服务所实现的营业收入总额，是反映企业经营业绩的核心指标。 | F4: 销售收入 = 当期所有确认履约的销售订单金额（含税）累计 | G4: 1. 周期：可按日、周、月、季度、年度统计； 2. 范围：已确认履约（出库/交付）的销售订单，不含作废、取消、未履约订单； 3. 计价：默认按不含税金额统计 | J4: T_SAL_OrderEntry | K4: FAmount | L4: SUM
A5: M003 | B5: 库存结存金额 | C5: 库存账面金额、期末库存价值 | D5: Inventory Balance Amount | E5: 在指定统计时点，仓库中所有物料、成品等库存物资按既定计价方式计算的账面总价值，反映企业库存资产规模。 | F5: 库存结存金额 = Σ（某物料结存数量 × 该物料当期计价单价），计价方式包括加权平均法、先进先出法等。 | G5: 1. 时点：指定具体日期（如月末、季末、年末）的期末时点； 2. 范围：企业所有仓库（含物理仓库、逻辑仓库）的全部库存物资，不含已出库未结算、已入库未入账物资； 3. 计价：按企业统一规定的计价方式执行，同一物料计价方式一致； | J5: T_STK_Inventory | K5: FOnHandAmt | L5: SUM
A6: M004 | B6: 库存结存数量 | C6: 库存实物数量、期末库存数 | D6: Inventory Balance Quantity | E6: 在指定统计时点，各仓库、库位实际留存的物料、成品等库存实物总数量，反映企业库存实物规模。 | F6: 库存结存数量 = 期初库存数量 + 当期入库总数量 - 当期出库总数量 | G6: 1. 时点：指定具体日期（如月末、季末、年末）的期末时点； 2. 范围：企业所有仓库的全部库存实物，含合格库存、待检库存，不含报废、冻结库存（按需调整）； 3. 计量：按物料既定计量单位统计（如个、件、吨），不跨计量单位汇总； | J6: T_STK_Inventory | K6: FOnHandQty | L6: SUM
A7: M005 | B7: 当月入库金额 | C7: 月度入库总金额、本月入库价值 | D7: Monthly Warehousing Amount | E7: 自然月内，所有入库单对应的物料、成品等物资累计入库总金额，反映月度库存增加的价值规模。 | F7: 当月入库金额 = 当月所有有效入库单（含采购入库、生产入库等）对应物资金额累计 | G7: 1. 周期：自然月（每月1日至当月月末）； 2. 范围：当月已审核、生效的入库单，不含作废、取消、未审核的入库单； 3. 计价：与库存计价方式一致，按不含税金额统计； | J7: T_STK_InvMovement | K7: FInAmt | L7: SUM
A8: M006 | B8: 当月出库金额 | C8: 月度出库总金额、本月出库价值 | D8: Monthly Outbound Amount | E8: 自然月内，所有出库单对应的物料、成品等物资累计出库总金额，反映月度库存减少的价值规模。 | F8: 当月出库金额 = 当月所有有效出库单（含销售出库、生产领用等）对应物资金额累计 | G8: 1. 周期：自然月（每月1日至当月月末）； 2. 范围：当月已审核、生效的出库单，不含作废、取消、未审核的出库单； 3. 计价：与库存计价方式一致，按不含税金额统计； | J8: T_STK_InvMovement | K8: FOutAmt | L8: SUM
A9: M007 | B9: 当月入库数量 | C9: 月度入库总数量、本月入库件数 | D9: Monthly Warehousing Quantity | E9: 自然月内，所有入库单记录的物料、成品等累计入库总数量，反映月度库存实物增加的规模。 | F9: 当月入库数量 = 当月所有有效入库单对应物资数量累计（按各物料计量单位汇总） | G9: 1. 周期：自然月（每月1日至当月月末）；2. 范围：当月已审核、生效的入库单，不含作废、取消、未审核的入库单；3. 计量：按物料既定计量单位统计，同类计量单位可汇总，不同计量单位分别统计；4. 关联维度：可按仓库、物料、入库类型维度拆分统计。 | J9: T_STK_InvMovement | K9: FInQty | L9: SUM
A10: M008 | B10: 当月出库数量 | C10: 月度出库总数量、本月出库件数 | D10: Monthly Outbound Quantity | E10: 自然月内，所有出库单记录的物料、成品等累计出库总数量，反映月度库存实物减少的规模。 | F10: 当月出库数量 = 当月所有有效出库单对应物资数量累计（按各物料计量单位汇总） | G10: 1. 周期：自然月（每月1日至当月月末）； 2. 范围：当月已审核、生效的出库单，不含作废、取消、未审核的出库单； 3. 计量：按物料既定计量单位统计，同类计量单位可汇总，不同计量单位分别统计； | J10: T_STK_InvMovement | K10: FOutQty | L10: SUM

Sheet 维度
A1: 维度编码 | B1: 维度名称 | C1: 维度别名 | D1: 维度英文名 | E1: 维度定义 | F1: 维度层级 | G1: 来源表 | H1: 来源字段
A2: D001 | B2: 时间维度 | C2: 周期维度、日期维度 | D2: Time Dimension | E2: 用于统计业务发生时间、划分统计周期的基础维度，支撑所有业务指标按时间范围的汇总、拆分与对比分析。 | F2: 5级（顶层：年度 → 季度 → 月度 → 周 → 日）
A3: D002 | B3: 组织维度 | C3: 机构维度、部门维度 | D3: Organization Dimension | E3: 用于划分企业内部权责与业务范围的核心维度，涵盖企业所有组织单元，用于关联业务单据、指标统计与权限管控。 | F3: 3级（顶层：公司/集团 → 中层：部门/事业部 → 底层：分支机构/仓库）
A4: D003 | B4: 客户维度 | C4: 客户分类维度、客户群体维度 | D4: Customer Dimension | E4: 用于区分不同客户群体、追溯销售业务来源的维度，关联客户基础信息，支撑销售收入、销售订单等指标的拆分统计。 | F4: 2级（顶层：客户类型 → 底层：具体客户）
A5: D004 | B5: 供应商维度 | C5: 供应商分类维度、供货方维度 | D5: Supplier Dimension | E5: 用于区分不同供应商、管控采购业务的维度，关联供应商基础信息，支撑采购金额、采购订单等指标的拆分统计。 | F5: 2级（顶层：供应商类型 → 底层：具体供应商）
A6: D005 | B6: 物料维度 | C6: 物料分类维度、产品维度 | D6: Material Dimension | E6: 用于划分物料类别、管控库存与交易的核心维度，关联物料基础信息，支撑库存、出入库、采购销售等所有相关指标统计。 | F6: 3级（顶层：物料大类 → 中层：物料子类 → 底层：具体物料）
A7: D006 | B7: 产品线维度 | C7: 产品系列维度、产品线分类维度 | D7: Product Line Dimension | E7: 用于划分产品集合、规划业务方向的维度，关联产品线信息，支撑销售收入、物料归属等指标的分类统计。 | F7: 2级（顶层：产品线大类 → 底层：具体产品线）
A8: D007 | B8: 仓库维度 | C8: 仓储维度、库位维度 | D8: Warehouse Dimension | E8: 用于划分库存存储空间、管控出入库业务的维度，关联仓库基础信息，支撑库存结存、出入库等指标的拆分统计。 | F8: 2级（顶层：仓库类型 → 底层：具体仓库/库位）

Sheet 指标维度矩阵
A1: 指标编码 | B1: 指标名称 | C1: 时间(期间) | D1: 组织 | E1: 仓库 | F1: 产品线 | G1: 物料 | H1: 计量单位 | I1: 客户 | J1: 供应商
A2: M001 | B2: 采购金额 | C2: Y | D2: Y | G2: Y | J2: Y
A3: M002 | B3: 销售收入 | C3: Y | D3: Y | F3: Y | I3: Y
A4: M003 | B4: 库存结存金额 | C4: Y | E4: Y | F4: Y | G4: Y
A5: M004 | B5: 库存结存数量 | C5: Y | E5: Y | F5: Y | H5: Y
A6: M005 | B6: 当月入库金额 | C6: Y | E6: Y | G6: Y
A7: M006 | B7: 当月出库金额 | C7: Y | E7: Y | G7: Y
A8: M007 | B8: 当月入库数量 | C8: Y | E8: Y | G8: Y | H8: Y
A9: M008 | B9: 当月出库数量 | C9: Y | E9: Y | G9: Y | H9: Y
